visdom_wrapper/__init__.py
visdom_wrapper/version.py
visdom_wrapper/visdom_wrapper.py
visdom_wrapper-0.1.0.dist-info/METADATA
visdom_wrapper-0.1.0.dist-info/RECORD
visdom_wrapper-0.1.0.dist-info/WHEEL
visdom_wrapper-0.1.0.dist-info/top_level.txt
