Metadata-Version: 2.1
Name: visdom-wrapper
Version: 0.1.0
Summary: A wrapper to use visdom with python 'with' statement.
Home-page: https://github.com/Queequeg92/visdom-wrapper
Author: Lv Chong
Author-email: lvchong24@gmail.com
License: UNKNOWN
Platform: UNKNOWN
Classifier: Programming Language :: Python :: 3
Classifier: License :: OSI Approved :: MIT License
Classifier: Operating System :: OS Independent
Requires-Dist: visdom (>=0.1.8.5)
